dps_stack/__init__.py
dps_stack-0.1.0.dist-info/WHEEL
dps_stack-0.1.0.dist-info/METADATA
dps_stack-0.1.0.dist-info/RECORD
