Metadata-Version: 2.1
Name: dps_stack
Version: 0.1.0
Summary: Helper functions and support functionality for dps-stack 
Home-page: UNKNOWN
License: UNKNOWN
Author: Jackie Vincent Larsen
Author-email: jackie.v.larsen@gmail.com
Classifier: License :: OSI Approved :: MIT License
